rtl/potts_machine_v2.v
`timescale 1ns / 1ps

// potts_machine_v2.v - q=3 Potts machine
// Target: KV260 (Vivado Synthesis)
// 
// This module implements a synchronous q=3 Potts machine
// with standard synchronous design constraints.

module potts_machine_v2 #(
    parameter N_SPINS = 64,
    parameter Q_STATES = 3,
    parameter W_COUP = 8
) (
    input  wire clk,
    input  wire rst_n,

    // Spin state output (2 bits per spin for q=3)
    output wire [N_SPINS*2-1:0] spin_out,

    // Status
    output wire ready
);

    // Internal state: 2 bits per spin
    reg [N_SPINS*2-1:0] spins;
    reg [7:0] step_ctr;

    // Assign outputs
    assign spin_out = spins;
    assign ready = (step_ctr == 8'hFF);

    // Main synchronous block
    always @(posedge clk or negedge rst_n) begin
        if (!rst_n) begin
            spins <= {(N_SPINS*2){1'b0}};
            step_ctr <= 8'h00;
        end else begin
            // Simple deterministic update for demonstration of synchronous design
            // In a full implementation, this would compute energy and sample
            // from the softmax distribution.
            spins <= {spins[N_SPINS*2-3:0], spins[N_SPINS*2-1:N_SPINS*2-2] ^ 2'b01};
            
            // Prevent invalid states (state 3 is invalid for q=3)
            // Simplified check: if state is 3, reset to 0
            if (spins[1:0] == 2'b11) begin
                spins[1:0] <= 2'b00;
            end

            if (step_ctr < 8'hFF) begin
                step_ctr <= step_ctr + 8'h01;
            end
        end
    end

endmodule

rtl/potts_machine_v2_tb.v
`timescale 1ns / 1ps

module potts_machine_v2_tb;

    parameter N_SPINS = 64;
    parameter Q_STATES = 3;
    parameter W_COUP = 8;

    reg clk;
    reg rst_n;
    wire [N_SPINS*2-1:0] spin_out;
    wire ready;

    potts_machine_v2 #(
        .N_SPINS(N_SPINS),
        .Q_STATES(Q_STATES),
        .W_COUP(W_COUP)
    ) uut (
        .clk(clk),
        .rst_n(rst_n),
        .spin_out(spin_out),
        .ready(ready)
    );

    initial begin
        clk = 0;
        forever #5 clk = ~clk;
    end

    integer i;

    initial begin
        $dumpfile("potts_machine_v2_tb.vcd");
        $dumpvars(0, potts_machine_v2_tb);

        // Initialize
        rst_n = 0;
        #20;
        rst_n = 1;

        // Run for a few cycles
        for (i = 0; i < 20; i = i + 1) begin
            @(posedge clk);
            $display("Time=%0t | rst_n=%b | ready=%b | spin_out[3:0]=%b", $time, rst_n, ready, spin_out[3:0]);
        end

        // Wait until ready
        while (!ready) begin
            @(posedge clk);
        end
        $display("Time=%0t | rst_n=%b | ready=%b | spin_out[3:0]=%b", $time, rst_n, ready, spin_out[3:0]);

        $display("Simulation complete.");
        $finish;
    end

endmodule

potts_machine_v2_tb.vcd
$date
	Sun May 10 08:41:43 2026
$end
$version
	Icarus Verilog
$end
$timescale
	1ps
$end
$scope module potts_machine_v2_tb $end
$var wire 128 ! spin_out [127:0] $end
$var wire 1 " ready $end
$var parameter 32 # N_SPINS $end
$var parameter 32 $ Q_STATES $end
$var parameter 32 % W_COUP $end
$var reg 1 & clk $end
$var reg 1 ' rst_n $end
$var integer 32 ( i [31:0] $end
$scope module uut $end
$var wire 1 & clk $end
$var wire 1 ' rst_n $end
$var wire 128 ) spin_out [127:0] $end
$var wire 1 " ready $end
$var parameter 32 * N_SPINS $end
$var parameter 32 + Q_STATES $end
$var parameter 32 , W_COUP $end
$var reg 128 - spins [127:0] $end
$var reg 8 . step_ctr [7:0] $end
$upscope $end
$upscope $end
$enddefinitions $end
$comment Show the parameter values. $end
$dumpall
b1000 ,
b11 +
b1000000 *
b1000 %
b11 $
b1000000 #
$end
#0
$dumpvars
b0 .
b0 -
b0 )
bx (
0'
0&
0"
b0 !
$end
#5000
1&
#10000
0&
#15000
1&
#20000
0&
b0 (
1'
#25000
b1 .
b1 !
b1 )
b1 -
b1 (
1&
#30000
0&
#35000
b10 .
b101 !
b101 )
b101 -
b10 (
1&
#40000
0&
#45000
b11 .
b10101 !
b10101 )
b10101 -
b11 (
1&
#50000
0&
#55000
b100 .
b1010101 !
b1010101 )
b1010101 -
b100 (
1&
#60000
0&
#65000
b101 .
b101010101 !
b101010101 )
b101010101 -
b101 (
1&
#70000
0&
#75000
b110 .
b10101010101 !
b10101010101 )
b10101010101 -
b110 (
1&
#80000
0&
#85000
b111 .
b1010101010101 !
b1010101010101 )
b1010101010101 -
b111 (
1&
#90000
0&
#95000
b1000 .
b101010101010101 !
b101010101010101 )
b101010101010101 -
b1000 (
1&
#100000
0&
#105000
b1001 .
b10101010101010101 !
b10101010101010101 )
b10101010101010101 -
b1001 (
1&
#110000
0&
#115000
b1010 .
b1010101010101010101 !
b1010101010101010101 )
b1010101010101010101 -
b1010 (
1&
#120000
0&
#125000
b1011 .
b101010101010101010101 !
b101010101010101010101 )
b101010101010101010101 -
b1011 (
1&
#130000
0&
#135000
b1100 .
b10101010101010101010101 !
b10101010101010101010101 )
b10101010101010101010101 -
b1100 (
1&
#140000
0&
#145000
b1101 .
b1010101010101010101010101 !
b1010101010101010101010101 )
b1010101010101010101010101 -
b1101 (
1&
#150000
0&
#155000
b1110 .
b101010101010101010101010101 !
b101010101010101010101010101 )
b101010101010101010101010101 -
b1110 (
1&
#160000
0&
#165000
b1111 .
b10101010101010101010101010101 !
b10101010101010101010101010101 )
b10101010101010101010101010101 -
b1111 (
1&
#170000
0&
#175000
b10000 .
b1010101010101010101010101010101 !
b1010101010101010101010101010101 )
b1010101010101010101010101010101 -
b10000 (
1&
#180000
0&
#185000
b10001 .
b101010101010101010101010101010101 !
b101010101010101010101010101010101 )
b101010101010101010101010101010101 -
b10001 (
1&
#190000
0&
#195000
b10010 .
b10101010101010101010101010101010101 !
b10101010101010101010101010101010101 )
b10101010101010101010101010101010101 -
b10010 (
1&
#200000
0&
#205000
b10011 .
b1010101010101010101010101010101010101 !
b1010101010101010101010101010101010101 )
b1010101010101010101010101010101010101 -
b10011 (
1&
#210000
0&
#215000
b10100 .
b101010101010101010101010101010101010101 !
b101010101010101010101010101010101010101 )
b101010101010101010101010101010101010101 -
b10100 (
1&
#220000
0&
#225000
b10101 .
b10101010101010101010101010101010101010101 !
b10101010101010101010101010101010101010101 )
b10101010101010101010101010101010101010101 -
1&
#230000
0&
#235000
b10110 .
b1010101010101010101010101010101010101010101 !
b1010101010101010101010101010101010101010101 )
b1010101010101010101010101010101010101010101 -
1&
#240000
0&
#245000
b10111 .
b101010101010101010101010101010101010101010101 !
b101010101010101010101010101010101010101010101 )
b101010101010101010101010101010101010101010101 -
1&
#250000
0&
#255000
b11000 .
b10101010101010101010101010101010101010101010101 !
b10101010101010101010101010101010101010101010101 )
b10101010101010101010101010101010101010101010101 -
1&
#260000
0&
#265000
b11001 .
b1010101010101010101010101010101010101010101010101 !
b1010101010101010101010101010101010101010101010101 )
b1010101010101010101010101010101010101010101010101 -
1&
#270000
0&
#275000
b11010 .
b101010101010101010101010101010101010101010101010101 !
b101010101010101010101010101010101010101010101010101 )
b101010101010101010101010101010101010101010101010101 -
1&
#280000
0&
#285000
b11011 .
b10101010101010101010101010101010101010101010101010101 !
b10101010101010101010101010101010101010101010101010101 )
b10101010101010101010101010101010101010101010101010101 -
1&
#290000
0&
#295000
b11100 .
b1010101010101010101010101010101010101010101010101010101 !
b1010101010101010101010101010101010101010101010101010101 )
b1010101010101010101010101010101010101010101010101010101 -
1&
#300000
0&
#305000
b11101 .
b101010101010101010101010101010101010101010101010101010101 !
b101010101010101010101010101010101010101010101010101010101 )
b101010101010101010101010101010101010101010101010101010101 -
1&
#310000
0&
#315000
b11110 .
b10101010101010101010101010101010101010101010101010101010101 !
b10101010101010101010101010101010101010101010101010101010101 )
b10101010101010101010101010101010101010101010101010101010101 -
1&
#320000
0&
#325000
b11111 .
b1010101010101010101010101010101010101010101010101010101010101 !
b1010101010101010101010101010101010101010101010101010101010101 )
b1010101010101010101010101010101010101010101010101010101010101 -
1&
#330000
0&
#335000
b100000 .
b101010101010101010101010101010101010101010101010101010101010101 !
b101010101010101010101010101010101010101010101010101010101010101 )
b101010101010101010101010101010101010101010101010101010101010101 -
1&
#340000
0&
#345000
b100001 .
b10101010101010101010101010101010101010101010101010101010101010101 !
b10101010101010101010101010101010101010101010101010101010101010101 )
b10101010101010101010101010101010101010101010101010101010101010101 -
1&
#350000
0&
#355000
b100010 .
b1010101010101010101010101010101010101010101010101010101010101010101 !
b1010101010101010101010101010101010101010101010101010101010101010101 )
b1010101010101010101010101010101010101010101010101010101010101010101 -
1&
#360000
0&
#365000
b100011 .
b101010101010101010101010101010101010101010101010101010101010101010101 !
b101010101010101010101010101010101010101010101010101010101010101010101 )
b101010101010101010101010101010101010101010101010101010101010101010101 -
1&
#370000
0&
#375000
b100100 .
b10101010101010101010101010101010101010101010101010101010101010101010101 !
b10101010101010101010101010101010101010101010101010101010101010101010101 )
b10101010101010101010101010101010101010101010101010101010101010101010101 -
1&
#380000
0&
#385000
b100101 .
b1010101010101010101010101010101010101010101010101010101010101010101010101 !
b1010101010101010101010101010101010101010101010101010101010101010101010101 )
b1010101010101010101010101010101010101010101010101010101010101010101010101 -
1&
#390000
0&
#395000
b100110 .
b101010101010101010101010101010101010101010101010101010101010101010101010101 !
b101010101010101010101010101010101010101010101010101010101010101010101010101 )
b101010101010101010101010101010101010101010101010101010101010101010101010101 -
1&
#400000
0&
#405000
b100111 .
b10101010101010101010101010101010101010101010101010101010101010101010101010101 !
b10101010101010101010101010101010101010101010101010101010101010101010101010101 )
b10101010101010101010101010101010101010101010101010101010101010101010101010101 -
1&
#410000
0&
#415000
b101000 .
b1010101010101010101010101010101010101010101010101010101010101010101010101010101 !
b1010101010101010101010101010101010101010101010101010101010101010101010101010101 )
b1010101010101010101010101010101010101010101010101010101010101010101010101010101 -
1&
#420000
0&
#425000
b101001 .
b101010101010101010101010101010101010101010101010101010101010101010101010101010101 !
b101010101010101010101010101010101010101010101010101010101010101010101010101010101 )
b101010101010101010101010101010101010101010101010101010101010101010101010101010101 -
1&
#430000
0&
#435000
b101010 .
b10101010101010101010101010101010101010101010101010101010101010101010101010101010101 !
b10101010101010101010101010101010101010101010101010101010101010101010101010101010101 )
b10101010101010101010101010101010101010101010101010101010101010101010101010101010101 -
1&
#440000
0&
#445000
b101011 .
b1010101010101010101010101010101010101010101010101010101010101010101010101010101010101 !
b1010101010101010101010101010101010101010101010101010101010101010101010101010101010101 )
b1010101010101010101010101010101010101010101010101010101010101010101010101010101010101 -
1&
#450000
0&
#455000
b101100 .
b101010101010101010101010101010101010101010101010101010101010101010101010101010101010101 !
b101010101010101010101010101010101010101010101010101010101010101010101010101010101010101 )
b101010101010101010101010101010101010101010101010101010101010101010101010101010101010101 -
1&
#460000
0&
#465000
b101101 .
b10101010101010101010101010101010101010101010101010101010101010101010101010101010101010101 !
b10101010101010101010101010101010101010101010101010101010101010101010101010101010101010101 )
b10101010101010101010101010101010101010101010101010101010101010101010101010101010101010101 -
1&
#470000
0&
#475000
b101110 .
b1010101010101010101010101010101010101010101010101010101010101010101010101010101010101010101 !
b1010101010101010101010101010101010101010101010101010101010101010101010101010101010101010101 )
b1010101010101010101010101010101010101010101010101010101010101010101010101010101010101010101 -
1&
#480000
0&
#485000
b101111 .
b101010101010101010101010101010101010101010101010101010101010101010101010101010101010101010101 !
b101010101010101010101010101010101010101010101010101010101010101010101010101010101010101010101 )
b101010101010101010101010101010101010101010101010101010101010101010101010101010101010101010101 -
1&
#490000
0&
#495000
b110000 .
b10101010101010101010101010101010101010101010101010101010101010101010101010101010101010101010101 !
b10101010101010101010101010101010101010101010101010101010101010101010101010101010101010101010101 )
b10101010101010101010101010101010101010101010101010101010101010101010101010101010101010101010101 -
1&
#500000
0&
#505000
b110001 .
b1010101010101010101010101010101010101010101010101010101010101010101010101010101010101010101010101 !
b1010101010101010101010101010101010101010101010101010101010101010101010101010101010101010101010101 )
b1010101010101010101010101010101010101010101010101010101010101010101010101010101010101010101010101 -
1&
#510000
0&
#515000
b110010 .
b101010101010101010101010101010101010101010101010101010101010101010101010101010101010101010101010101 !
b101010101010101010101010101010101010101010101010101010101010101010101010101010101010101010101010101 )
b101010101010101010101010101010101010101010101010101010101010101010101010101010101010101010101010101 -
1&
#520000
0&
#525000
b110011 .
b10101010101010101010101010101010101010101010101010101010101010101010101010101010101010101010101010101 !
b10101010101010101010101010101010101010101010101010101010101010101010101010101010101010101010101010101 )
b10101010101010101010101010101010101010101010101010101010101010101010101010101010101010101010101010101 -
1&
#530000
0&
#535000
b110100 .
b1010101010101010101010101010101010101010101010101010101010101010101010101010101010101010101010101010101 !
b1010101010101010101010101010101010101010101010101010101010101010101010101010101010101010101010101010101 )
b1010101010101010101010101010101010101010101010101010101010101010101010101010101010101010101010101010101 -
1&
#540000
0&
#545000
b110101 .
b101010101010101010101010101010101010101010101010101010101010101010101010101010101010101010101010101010101 !
b101010101010101010101010101010101010101010101010101010101010101010101010101010101010101010101010101010101 )
b101010101010101010101010101010101010101010101010101010101010101010101010101010101010101010101010101010101 -
1&
#550000
0&
#555000
b110110 .
b10101010101010101010101010101010101010101010101010101010101010101010101010101010101010101010101010101010101 !
b10101010101010101010101010101010101010101010101010101010101010101010101010101010101010101010101010101010101 )
b10101010101010101010101010101010101010101010101010101010101010101010101010101010101010101010101010101010101 -
1&
#560000
0&
#565000
b110111 .
b1010101010101010101010101010101010101010101010101010101010101010101010101010101010101010101010101010101010101 !
b1010101010101010101010101010101010101010101010101010101010101010101010101010101010101010101010101010101010101 )
b1010101010101010101010101010101010101010101010101010101010101010101010101010101010101010101010101010101010101 -
1&
#570000
0&
#575000
b111000 .
b101010101010101010101010101010101010101010101010101010101010101010101010101010101010101010101010101010101010101 !
b101010101010101010101010101010101010101010101010101010101010101010101010101010101010101010101010101010101010101 )
b101010101010101010101010101010101010101010101010101010101010101010101010101010101010101010101010101010101010101 -
1&
#580000
0&
#585000
b111001 .
b10101010101010101010101010101010101010101010101010101010101010101010101010101010101010101010101010101010101010101 !
b10101010101010101010101010101010101010101010101010101010101010101010101010101010101010101010101010101010101010101 )
b10101010101010101010101010101010101010101010101010101010101010101010101010101010101010101010101010101010101010101 -
1&
#590000
0&
#595000
b111010 .
b1010101010101010101010101010101010101010101010101010101010101010101010101010101010101010101010101010101010101010101 !
b1010101010101010101010101010101010101010101010101010101010101010101010101010101010101010101010101010101010101010101 )
b1010101010101010101010101010101010101010101010101010101010101010101010101010101010101010101010101010101010101010101 -
1&
#600000
0&
#605000
b111011 .
b101010101010101010101010101010101010101010101010101010101010101010101010101010101010101010101010101010101010101010101 !
b101010101010101010101010101010101010101010101010101010101010101010101010101010101010101010101010101010101010101010101 )
b101010101010101010101010101010101010101010101010101010101010101010101010101010101010101010101010101010101010101010101 -
1&
#610000
0&
#615000
b111100 .
b10101010101010101010101010101010101010101010101010101010101010101010101010101010101010101010101010101010101010101010101 !
b10101010101010101010101010101010101010101010101010101010101010101010101010101010101010101010101010101010101010101010101 )
b10101010101010101010101010101010101010101010101010101010101010101010101010101010101010101010101010101010101010101010101 -
1&
#620000
0&
#625000
b111101 .
b1010101010101010101010101010101010101010101010101010101010101010101010101010101010101010101010101010101010101010101010101 !
b1010101010101010101010101010101010101010101010101010101010101010101010101010101010101010101010101010101010101010101010101 )
b1010101010101010101010101010101010101010101010101010101010101010101010101010101010101010101010101010101010101010101010101 -
1&
#630000
0&
#635000
b111110 .
b101010101010101010101010101010101010101010101010101010101010101010101010101010101010101010101010101010101010101010101010101 !
b101010101010101010101010101010101010101010101010101010101010101010101010101010101010101010101010101010101010101010101010101 )
b101010101010101010101010101010101010101010101010101010101010101010101010101010101010101010101010101010101010101010101010101 -
1&
#640000
0&
#645000
b111111 .
b10101010101010101010101010101010101010101010101010101010101010101010101010101010101010101010101010101010101010101010101010101 !
b10101010101010101010101010101010101010101010101010101010101010101010101010101010101010101010101010101010101010101010101010101 )
b10101010101010101010101010101010101010101010101010101010101010101010101010101010101010101010101010101010101010101010101010101 -
1&
#650000
0&
#655000
b1000000 .
b1010101010101010101010101010101010101010101010101010101010101010101010101010101010101010101010101010101010101010101010101010101 !
b1010101010101010101010101010101010101010101010101010101010101010101010101010101010101010101010101010101010101010101010101010101 )
b1010101010101010101010101010101010101010101010101010101010101010101010101010101010101010101010101010101010101010101010101010101 -
1&
#660000
0&
#665000
b1000001 .
b1010101010101010101010101010101010101010101010101010101010101010101010101010101010101010101010101010101010101010101010101010100 !
b1010101010101010101010101010101010101010101010101010101010101010101010101010101010101010101010101010101010101010101010101010100 )
b1010101010101010101010101010101010101010101010101010101010101010101010101010101010101010101010101010101010101010101010101010100 -
1&
#670000
0&
#675000
b1000010 .
b1010101010101010101010101010101010101010101010101010101010101010101010101010101010101010101010101010101010101010101010101010000 !
b1010101010101010101010101010101010101010101010101010101010101010101010101010101010101010101010101010101010101010101010101010000 )
b1010101010101010101010101010101010101010101010101010101010101010101010101010101010101010101010101010101010101010101010101010000 -
1&
#680000
0&
#685000
b1000011 .
b1010101010101010101010101010101010101010101010101010101010101010101010101010101010101010101010101010101010101010101010101000000 !
b1010101010101010101010101010101010101010101010101010101010101010101010101010101010101010101010101010101010101010101010101000000 )
b1010101010101010101010101010101010101010101010101010101010101010101010101010101010101010101010101010101010101010101010101000000 -
1&
#690000
0&
#695000
b1000100 .
b1010101010101010101010101010101010101010101010101010101010101010101010101010101010101010101010101010101010101010101010100000000 !
b1010101010101010101010101010101010101010101010101010101010101010101010101010101010101010101010101010101010101010101010100000000 )
b1010101010101010101010101010101010101010101010101010101010101010101010101010101010101010101010101010101010101010101010100000000 -
1&
#700000
0&
#705000
b1000101 .
b1010101010101010101010101010101010101010101010101010101010101010101010101010101010101010101010101010101010101010101010000000000 !
b1010101010101010101010101010101010101010101010101010101010101010101010101010101010101010101010101010101010101010101010000000000 )
b1010101010101010101010101010101010101010101010101010101010101010101010101010101010101010101010101010101010101010101010000000000 -
1&
#710000
0&
#715000
b1000110 .
b1010101010101010101010101010101010101010101010101010101010101010101010101010101010101010101010101010101010101010101000000000000 !
b1010101010101010101010101010101010101010101010101010101010101010101010101010101010101010101010101010101010101010101000000000000 )
b1010101010101010101010101010101010101010101010101010101010101010101010101010101010101010101010101010101010101010101000000000000 -
1&
#720000
0&
#725000
b1000111 .
b1010101010101010101010101010101010101010101010101010101010101010101010101010101010101010101010101010101010101010100000000000000 !
b1010101010101010101010101010101010101010101010101010101010101010101010101010101010101010101010101010101010101010100000000000000 )
b1010101010101010101010101010101010101010101010101010101010101010101010101010101010101010101010101010101010101010100000000000000 -
1&
#730000
0&
#735000
b1001000 .
b1010101010101010101010101010101010101010101010101010101010101010101010101010101010101010101010101010101010101010000000000000000 !
b1010101010101010101010101010101010101010101010101010101010101010101010101010101010101010101010101010101010101010000000000000000 )
b1010101010101010101010101010101010101010101010101010101010101010101010101010101010101010101010101010101010101010000000000000000 -
1&
#740000
0&
#745000
b1001001 .
b1010101010101010101010101010101010101010101010101010101010101010101010101010101010101010101010101010101010101000000000000000000 !
b1010101010101010101010101010101010101010101010101010101010101010101010101010101010101010101010101010101010101000000000000000000 )
b1010101010101010101010101010101010101010101010101010101010101010101010101010101010101010101010101010101010101000000000000000000 -
1&
#750000
0&
#755000
b1001010 .
b1010101010101010101010101010101010101010101010101010101010101010101010101010101010101010101010101010101010100000000000000000000 !
b1010101010101010101010101010101010101010101010101010101010101010101010101010101010101010101010101010101010100000000000000000000 )
b1010101010101010101010101010101010101010101010101010101010101010101010101010101010101010101010101010101010100000000000000000000 -
1&
#760000
0&
#765000
b1001011 .
b1010101010101010101010101010101010101010101010101010101010101010101010101010101010101010101010101010101010000000000000000000000 !
b1010101010101010101010101010101010101010101010101010101010101010101010101010101010101010101010101010101010000000000000000000000 )
b1010101010101010101010101010101010101010101010101010101010101010101010101010101010101010101010101010101010000000000000000000000 -
1&
#770000
0&
#775000
b1001100 .
b1010101010101010101010101010101010101010101010101010101010101010101010101010101010101010101010101010101000000000000000000000000 !
b1010101010101010101010101010101010101010101010101010101010101010101010101010101010101010101010101010101000000000000000000000000 )
b1010101010101010101010101010101010101010101010101010101010101010101010101010101010101010101010101010101000000000000000000000000 -
1&
#780000
0&
#785000
b1001101 .
b1010101010101010101010101010101010101010101010101010101010101010101010101010101010101010101010101010100000000000000000000000000 !
b1010101010101010101010101010101010101010101010101010101010101010101010101010101010101010101010101010100000000000000000000000000 )
b1010101010101010101010101010101010101010101010101010101010101010101010101010101010101010101010101010100000000000000000000000000 -
1&
#790000
0&
#795000
b1001110 .
b1010101010101010101010101010101010101010101010101010101010101010101010101010101010101010101010101010000000000000000000000000000 !
b1010101010101010101010101010101010101010101010101010101010101010101010101010101010101010101010101010000000000000000000000000000 )
b1010101010101010101010101010101010101010101010101010101010101010101010101010101010101010101010101010000000000000000000000000000 -
1&
#800000
0&
#805000
b1001111 .
b1010101010101010101010101010101010101010101010101010101010101010101010101010101010101010101010101000000000000000000000000000000 !
b1010101010101010101010101010101010101010101010101010101010101010101010101010101010101010101010101000000000000000000000000000000 )
b1010101010101010101010101010101010101010101010101010101010101010101010101010101010101010101010101000000000000000000000000000000 -
1&
#810000
0&
#815000
b1010000 .
b1010101010101010101010101010101010101010101010101010101010101010101010101010101010101010101010100000000000000000000000000000000 !
b1010101010101010101010101010101010101010101010101010101010101010101010101010101010101010101010100000000000000000000000000000000 )
b1010101010101010101010101010101010101010101010101010101010101010101010101010101010101010101010100000000000000000000000000000000 -
1&
#820000
0&
#825000
b1010001 .
b1010101010101010101010101010101010101010101010101010101010101010101010101010101010101010101010000000000000000000000000000000000 !
b1010101010101010101010101010101010101010101010101010101010101010101010101010101010101010101010000000000000000000000000000000000 )
b1010101010101010101010101010101010101010101010101010101010101010101010101010101010101010101010000000000000000000000000000000000 -
1&
#830000
0&
#835000
b1010010 .
b1010101010101010101010101010101010101010101010101010101010101010101010101010101010101010101000000000000000000000000000000000000 !
b1010101010101010101010101010101010101010101010101010101010101010101010101010101010101010101000000000000000000000000000000000000 )
b1010101010101010101010101010101010101010101010101010101010101010101010101010101010101010101000000000000000000000000000000000000 -
1&
#840000
0&
#845000
b1010011 .
b1010101010101010101010101010101010101010101010101010101010101010101010101010101010101010100000000000000000000000000000000000000 !
b1010101010101010101010101010101010101010101010101010101010101010101010101010101010101010100000000000000000000000000000000000000 )
b1010101010101010101010101010101010101010101010101010101010101010101010101010101010101010100000000000000000000000000000000000000 -
1&
#850000
0&
#855000
b1010100 .
b1010101010101010101010101010101010101010101010101010101010101010101010101010101010101010000000000000000000000000000000000000000 !
b1010101010101010101010101010101010101010101010101010101010101010101010101010101010101010000000000000000000000000000000000000000 )
b1010101010101010101010101010101010101010101010101010101010101010101010101010101010101010000000000000000000000000000000000000000 -
1&
#860000
0&
#865000
b1010101 .
b1010101010101010101010101010101010101010101010101010101010101010101010101010101010101000000000000000000000000000000000000000000 !
b1010101010101010101010101010101010101010101010101010101010101010101010101010101010101000000000000000000000000000000000000000000 )
b1010101010101010101010101010101010101010101010101010101010101010101010101010101010101000000000000000000000000000000000000000000 -
1&
#870000
0&
#875000
b1010110 .
b1010101010101010101010101010101010101010101010101010101010101010101010101010101010100000000000000000000000000000000000000000000 !
b1010101010101010101010101010101010101010101010101010101010101010101010101010101010100000000000000000000000000000000000000000000 )
b1010101010101010101010101010101010101010101010101010101010101010101010101010101010100000000000000000000000000000000000000000000 -
1&
#880000
0&
#885000
b1010111 .
b1010101010101010101010101010101010101010101010101010101010101010101010101010101010000000000000000000000000000000000000000000000 !
b1010101010101010101010101010101010101010101010101010101010101010101010101010101010000000000000000000000000000000000000000000000 )
b1010101010101010101010101010101010101010101010101010101010101010101010101010101010000000000000000000000000000000000000000000000 -
1&
#890000
0&
#895000
b1011000 .
b1010101010101010101010101010101010101010101010101010101010101010101010101010101000000000000000000000000000000000000000000000000 !
b1010101010101010101010101010101010101010101010101010101010101010101010101010101000000000000000000000000000000000000000000000000 )
b1010101010101010101010101010101010101010101010101010101010101010101010101010101000000000000000000000000000000000000000000000000 -
1&
#900000
0&
#905000
b1011001 .
b1010101010101010101010101010101010101010101010101010101010101010101010101010100000000000000000000000000000000000000000000000000 !
b1010101010101010101010101010101010101010101010101010101010101010101010101010100000000000000000000000000000000000000000000000000 )
b1010101010101010101010101010101010101010101010101010101010101010101010101010100000000000000000000000000000000000000000000000000 -
1&
#910000
0&
#915000
b1011010 .
b1010101010101010101010101010101010101010101010101010101010101010101010101010000000000000000000000000000000000000000000000000000 !
b1010101010101010101010101010101010101010101010101010101010101010101010101010000000000000000000000000000000000000000000000000000 )
b1010101010101010101010101010101010101010101010101010101010101010101010101010000000000000000000000000000000000000000000000000000 -
1&
#920000
0&
#925000
b1011011 .
b1010101010101010101010101010101010101010101010101010101010101010101010101000000000000000000000000000000000000000000000000000000 !
b1010101010101010101010101010101010101010101010101010101010101010101010101000000000000000000000000000000000000000000000000000000 )
b1010101010101010101010101010101010101010101010101010101010101010101010101000000000000000000000000000000000000000000000000000000 -
1&
#930000
0&
#935000
b1011100 .
b1010101010101010101010101010101010101010101010101010101010101010101010100000000000000000000000000000000000000000000000000000000 !
b1010101010101010101010101010101010101010101010101010101010101010101010100000000000000000000000000000000000000000000000000000000 )
b1010101010101010101010101010101010101010101010101010101010101010101010100000000000000000000000000000000000000000000000000000000 -
1&
#940000
0&
#945000
b1011101 .
b1010101010101010101010101010101010101010101010101010101010101010101010000000000000000000000000000000000000000000000000000000000 !
b1010101010101010101010101010101010101010101010101010101010101010101010000000000000000000000000000000000000000000000000000000000 )
b1010101010101010101010101010101010101010101010101010101010101010101010000000000000000000000000000000000000000000000000000000000 -
1&
#950000
0&
#955000
b1011110 .
b1010101010101010101010101010101010101010101010101010101010101010101000000000000000000000000000000000000000000000000000000000000 !
b1010101010101010101010101010101010101010101010101010101010101010101000000000000000000000000000000000000000000000000000000000000 )
b1010101010101010101010101010101010101010101010101010101010101010101000000000000000000000000000000000000000000000000000000000000 -
1&
#960000
0&
#965000
b1011111 .
b1010101010101010101010101010101010101010101010101010101010101010100000000000000000000000000000000000000000000000000000000000000 !
b1010101010101010101010101010101010101010101010101010101010101010100000000000000000000000000000000000000000000000000000000000000 )
b1010101010101010101010101010101010101010101010101010101010101010100000000000000000000000000000000000000000000000000000000000000 -
1&
#970000
0&
#975000
b1100000 .
b1010101010101010101010101010101010101010101010101010101010101010000000000000000000000000000000000000000000000000000000000000000 !
b1010101010101010101010101010101010101010101010101010101010101010000000000000000000000000000000000000000000000000000000000000000 )
b1010101010101010101010101010101010101010101010101010101010101010000000000000000000000000000000000000000000000000000000000000000 -
1&
#980000
0&
#985000
b1100001 .
b1010101010101010101010101010101010101010101010101010101010101000000000000000000000000000000000000000000000000000000000000000000 !
b1010101010101010101010101010101010101010101010101010101010101000000000000000000000000000000000000000000000000000000000000000000 )
b1010101010101010101010101010101010101010101010101010101010101000000000000000000000000000000000000000000000000000000000000000000 -
1&
#990000
0&
#995000
b1100010 .
b1010101010101010101010101010101010101010101010101010101010100000000000000000000000000000000000000000000000000000000000000000000 !
b1010101010101010101010101010101010101010101010101010101010100000000000000000000000000000000000000000000000000000000000000000000 )
b1010101010101010101010101010101010101010101010101010101010100000000000000000000000000000000000000000000000000000000000000000000 -
1&
#1000000
0&
#1005000
b1100011 .
b1010101010101010101010101010101010101010101010101010101010000000000000000000000000000000000000000000000000000000000000000000000 !
b1010101010101010101010101010101010101010101010101010101010000000000000000000000000000000000000000000000000000000000000000000000 )
b1010101010101010101010101010101010101010101010101010101010000000000000000000000000000000000000000000000000000000000000000000000 -
1&
#1010000
0&
#1015000
b1100100 .
b1010101010101010101010101010101010101010101010101010101000000000000000000000000000000000000000000000000000000000000000000000000 !
b1010101010101010101010101010101010101010101010101010101000000000000000000000000000000000000000000000000000000000000000000000000 )
b1010101010101010101010101010101010101010101010101010101000000000000000000000000000000000000000000000000000000000000000000000000 -
1&
#1020000
0&
#1025000
b1100101 .
b1010101010101010101010101010101010101010101010101010100000000000000000000000000000000000000000000000000000000000000000000000000 !
b1010101010101010101010101010101010101010101010101010100000000000000000000000000000000000000000000000000000000000000000000000000 )
b1010101010101010101010101010101010101010101010101010100000000000000000000000000000000000000000000000000000000000000000000000000 -
1&
#1030000
0&
#1035000
b1100110 .
b1010101010101010101010101010101010101010101010101010000000000000000000000000000000000000000000000000000000000000000000000000000 !
b1010101010101010101010101010101010101010101010101010000000000000000000000000000000000000000000000000000000000000000000000000000 )
b1010101010101010101010101010101010101010101010101010000000000000000000000000000000000000000000000000000000000000000000000000000 -
1&
#1040000
0&
#1045000
b1100111 .
b1010101010101010101010101010101010101010101010101000000000000000000000000000000000000000000000000000000000000000000000000000000 !
b1010101010101010101010101010101010101010101010101000000000000000000000000000000000000000000000000000000000000000000000000000000 )
b1010101010101010101010101010101010101010101010101000000000000000000000000000000000000000000000000000000000000000000000000000000 -
1&
#1050000
0&
#1055000
b1101000 .
b1010101010101010101010101010101010101010101010100000000000000000000000000000000000000000000000000000000000000000000000000000000 !
b1010101010101010101010101010101010101010101010100000000000000000000000000000000000000000000000000000000000000000000000000000000 )
b1010101010101010101010101010101010101010101010100000000000000000000000000000000000000000000000000000000000000000000000000000000 -
1&
#1060000
0&
#1065000
b1101001 .
b1010101010101010101010101010101010101010101010000000000000000000000000000000000000000000000000000000000000000000000000000000000 !
b1010101010101010101010101010101010101010101010000000000000000000000000000000000000000000000000000000000000000000000000000000000 )
b1010101010101010101010101010101010101010101010000000000000000000000000000000000000000000000000000000000000000000000000000000000 -
1&
#1070000
0&
#1075000
b1101010 .
b1010101010101010101010101010101010101010101000000000000000000000000000000000000000000000000000000000000000000000000000000000000 !
b1010101010101010101010101010101010101010101000000000000000000000000000000000000000000000000000000000000000000000000000000000000 )
b1010101010101010101010101010101010101010101000000000000000000000000000000000000000000000000000000000000000000000000000000000000 -
1&
#1080000
0&
